[
  {
    "Order-Id": "#12512B",
    "Date": "May 5, 4:20 PM",
    "customer": "Tom Anderson",
    "payment-status": "Paid",
    "order-status": "Ready",
    "price": "$49.90"
  },
  {
    "Order-Id": "#12523C",
    "Date": "May 5, 4:15 PM",
    "customer": "Jayden Walker",
    "payment-status": "Paid",
    "order-status": "Ready",
    "price": "$34.36"
  },
  {
    "Order-Id": "#51232A",
    "Date": "May 5, 4:15 PM",
    "customer": "Inez Kim",
    "payment-status": "Paid",
    "order-status": "Ready",
    "price": "$5.51"
  },
  {
    "Order-Id": "#23534D",
    "Date": "May 5, 4:12 PM",
    "customer": "Francisco Henry",
    "payment-status": "Paid",
    "order-status": "Shipped",
    "price": "$29.74"
  },
  {
    "Order-Id": "#51323C",
    "Date": "May 5, 4:12 PM",
    "customer": "Violet Phillips",
    "payment-status": "Paid",
    "order-status": "Shipped",
    "price": "$23.06"
  },
  {
    "Order-Id": "#35622A",
    "Date": "May 5, 4:12 PM",
    "customer": "Rosetta Becker",
    "payment-status": "Paid",
    "order-status": "Shipped",
    "price": "$87.44"
  },
  {
    "Order-Id": "#34232D",
    "Date": "May 5, 4:10 PM",
    "customer": "Dean Love",
    "payment-status": "Paid",
    "order-status": "Ready",
    "price": "$44.55"
  },
  {
    "Order-Id": "#56212D",
    "Date": "May 5, 4:08 PM",
    "customer": "Nettie Tyler",
    "payment-status": "Paid",
    "order-status": "Ready",
    "price": "$36.79"
  },
  {
    "Order-Id": "#76543E",
    "Date": "May 5, 4:08 PM",
    "customer": "Lora Weaver",
    "payment-status": "Paid",
    "order-status": "Shipped",
    "price": "$28.78"
  },
  {
    "Order-Id": "#12512B",
    "Date": "May 5, 4:05 PM",
    "customer": "Vincent Cannon",
    "payment-status": "Paid",
    "order-status": "Shipped",
    "price": "$96.46"
  },
  {
    "Order-Id": "#12523C",
    "Date": "May 5, 4:05 PM",
    "customer": "Nettie Palmer",
    "payment-status": "Paid",
    "order-status": "Received",
    "price": "$25.53"
  },
  {
    "Order-Id": "#23534D",
    "Date": "May 5, 4:04 PM",
    "customer": "Miguel Harris",
    "payment-status": "Pending",
    "order-status": "Ready",
    "price": "$50.54"
  },
  {
    "Order-Id": "#12523C",
    "Date": "May 5, 4:04 PM",
    "customer": "Angel Conner",
    "payment-status": "Pending",
    "order-status": "Ready",
    "price": "$63.47"
  },
  {
    "Order-Id": "#51232A",
    "Date": "May 5, 4:03 PM",
    "customer": "Rosalie Singleton",
    "payment-status": "Pending",
    "order-status": "Received",
    "price": "$91.63"
  }
]
